aws_cdk_secure_api/__init__.py
aws_cdk_secure_api/__version__.py
aws_cdk_secure_api/api_construct.py
aws_cdk_secure_api/cache.py
aws_cdk_secure_api/models.py
aws_cdk_secure_api/aws/__init__.py
aws_cdk_secure_api/aws/client_cache.py
aws_cdk_secure_api/aws/secrets_manager.py
aws_cdk_secure_api/aws/ssm_parameter_store.py
aws_cdk_secure_api-0.5.0.dist-info/LICENSE
aws_cdk_secure_api-0.5.0.dist-info/METADATA
aws_cdk_secure_api-0.5.0.dist-info/WHEEL
aws_cdk_secure_api-0.5.0.dist-info/top_level.txt
aws_cdk_secure_api-0.5.0.dist-info/RECORD
