Metadata-Version: 2.1
Name: aws-cdk-secure-api
Version: 0.5.0
Summary: A CDK (v2) Construct Library for Secure REST APIs
Home-page: https://github.com/rnag/aws-cdk-secure-api
Author: Ritvik Nag
Author-email: rv.kvetch@gmail.com
License: MIT
Project-URL: Documentation, https://aws-cdk-secure-api.readthedocs.io
Project-URL: Source, https://github.com/rnag/aws-cdk-secure-api
Keywords: aws-cdk,secure,rest-api,api-gateway,api key,cdk
Platform: UNKNOWN
Classifier: Development Status :: 4 - Beta
Classifier: Intended Audience :: Developers
Classifier: License :: OSI Approved :: MIT License
Classifier: Natural Language :: English
Classifier: Programming Language :: Python :: 3 :: Only
Classifier: Programming Language :: Python :: 3
Classifier: Programming Language :: Python :: 3.7
Classifier: Programming Language :: Python :: 3.8
Classifier: Programming Language :: Python :: 3.9
Classifier: Programming Language :: Python :: 3.10
Classifier: Programming Language :: Python :: 3.11
Classifier: Programming Language :: Python
Requires-Dist: aws-cdk-lib (<3.0.0,>=2.0.0)
Requires-Dist: constructs (<11.0.0,>=10.0.0)
Requires-Dist: boto3 (<2.0.0,>=1.0.0)
